MANIFEST.in
README.rst
setup.cfg
setup.py
docs/CHANGES.rst
docs/CONTRIBUTORS.rst
docs/LICENSE.GPL
docs/LICENSE.rst
docs/index.rst
src/c2/__init__.py
src/c2.patch.jasplitter.egg-info/PKG-INFO
src/c2.patch.jasplitter.egg-info/SOURCES.txt
src/c2.patch.jasplitter.egg-info/dependency_links.txt
src/c2.patch.jasplitter.egg-info/entry_points.txt
src/c2.patch.jasplitter.egg-info/namespace_packages.txt
src/c2.patch.jasplitter.egg-info/not-zip-safe
src/c2.patch.jasplitter.egg-info/requires.txt
src/c2.patch.jasplitter.egg-info/top_level.txt
src/c2/patch/__init__.py
src/c2/patch/jasplitter/__init__.py
src/c2/patch/jasplitter/monkey.py
src/c2/patch/jasplitter/testing.py
src/c2/patch/jasplitter/tests/__init__.py
src/c2/patch/jasplitter/tests/test_pathes.py