Metadata-Version: 1.1
Name: c2.patch.jasplitter
Version: 1.0a2
Summary: This product is bugfix splitter of Plone for Japanese.
Home-page: https://pypi.python.org/pypi/c2.patch.jasplitter
Author: Manabu TERADA
Author-email: terada@cmscom.jp
License: GPL version 2
Keywords: Python Plone
Platform: UNKNOWN
Classifier: Environment :: Web Environment
Classifier: Framework :: Plone
Classifier: Framework :: Plone :: 5.0
Classifier: Programming Language :: Python
Classifier: Programming Language :: Python :: 2.7
Classifier: Operating System :: OS Independent
Classifier: License :: OSI Approved :: GNU General Public License v2 (GPLv2)
